{
  "variants": {
    "age=0": { "model": "worldsubstance:block/plant_rosemary_stage0" },
    "age=1": { "model": "worldsubstance:block/plant_rosemary_stage1" },
    "age=2,wild=true": { "model": "worldsubstance:block/plant_rosemary_stage2_wild" },
    "age=2,wild=false": { "model": "worldsubstance:block/plant_rosemary_stage2_domestic" },
    "age=3,wild=true": { "model": "worldsubstance:block/plant_rosemary_stage3_wild" },
    "age=3,wild=false": { "model": "worldsubstance:block/plant_rosemary_stage3_domestic" }
  }
}